tool2schema/__init__.py
tool2schema/config.py
tool2schema/parameter_schema.py
tool2schema/py.typed
tool2schema/schema.py
tool2schema/type_schema.py
tool2schema-2.2.0.dist-info/LICENSE
tool2schema-2.2.0.dist-info/METADATA
tool2schema-2.2.0.dist-info/WHEEL
tool2schema-2.2.0.dist-info/RECORD
