Metadata-Version: 2.1
Name: tool2schema
Version: 2.2.0
Summary: A library to generate function schemas for use in LLM function calling.
Home-page: https://github.com/cadifyai/tool2schema
License: Apache-2.0
Keywords: openai,llm
Author: Angus Stewart
Author-email: siliconlad@protonmail.com
Requires-Python: >=3.9,<4.0
Classifier: License :: OSI Approved :: Apache Software License
Classifier: Programming Language :: Python :: 3
Classifier: Programming Language :: Python :: 3.9
Classifier: Programming Language :: Python :: 3.10
Classifier: Programming Language :: Python :: 3.11
Classifier: Programming Language :: Python :: 3.12
Project-URL: Repository, https://github.com/cadifyai/tool2schema
